git2jss/__init__.py
git2jss/exceptions.py
git2jss/jss_keyring.py
git2jss/processors.py
git2jss/vcs.py
git2jss-2.0.1.dist-info/LICENSE
git2jss-2.0.1.dist-info/METADATA
git2jss-2.0.1.dist-info/WHEEL
git2jss-2.0.1.dist-info/entry_points.txt
git2jss-2.0.1.dist-info/top_level.txt
git2jss-2.0.1.dist-info/RECORD
