Metadata-Version: 2.1
Name: git2jss
Version: 2.0.1
Summary: Push scripts from a Git repo to a JSS. Includes templating and tagging.
Home-page: https://github.com/gkluoe/git2jss
Author: Geoff Lee
Author-email: g.lee@ed.ac.uk
License: Apache Software License
Download-URL: https://github.com/gkluoe/git2jss/tarball/v2.0.1
Keywords: JAMF jss git release
Platform: UNKNOWN
Classifier: Development Status :: 4 - Beta
Classifier: Intended Audience :: Developers
Classifier: License :: OSI Approved :: Apache Software License
Classifier: Programming Language :: Python :: 2
Requires-Dist: python-jss
Requires-Dist: keyring
